src/__init__.py
src/cli.py
oslili_cli-0.8.dist-info/LICENSE
oslili_cli-0.8.dist-info/METADATA
oslili_cli-0.8.dist-info/NOTICE
oslili_cli-0.8.dist-info/WHEEL
oslili_cli-0.8.dist-info/entry_points.txt
oslili_cli-0.8.dist-info/top_level.txt
oslili_cli-0.8.dist-info/RECORD
